compute_mcp_service/__init__.py
compute_mcp_service/__main__.py
compute_mcp_service/server.py
compute_mcp-0.1.5.dist-info/METADATA
compute_mcp-0.1.5.dist-info/WHEEL
compute_mcp-0.1.5.dist-info/entry_points.txt
compute_mcp-0.1.5.dist-info/RECORD
