Metadata-Version: 2.4
Name: compute-mcp
Version: 0.1.5
Summary: Add your description here
Requires-Python: >=3.13
Requires-Dist: build>=1.2.2.post1
Requires-Dist: fastmcp>=2.12.3
Requires-Dist: twine>=6.1.0
